hide/__init__.py
swillow-0.0.1.dist-info/LICENSE.txt
swillow-0.0.1.dist-info/METADATA
swillow-0.0.1.dist-info/WHEEL
swillow-0.0.1.dist-info/top_level.txt
swillow-0.0.1.dist-info/RECORD
