Metadata-Version: 2.1
Name: swillow
Version: 0.0.1
Summary: add
Home-page: UNKNOWN
Author: Adetayo Ademola
Author-email: adetayoty@gmail.com
License: UNKNOWN
Platform: UNKNOWN
Classifier: Programming Language :: Python :: 3
Classifier: License :: OSI Approved :: MIT License
Classifier: Operating System :: OS Independent
